etcdstat/__init__.py
etcdstat/_version.py
etcdstat/complexini.py
etcdstat/cpu.py
etcdstat/disk.py
etcdstat/etcdstat.py
etcdstat/host.py
etcdstat/memory.py
etcdstat/module.py
etcdstat/os_support.py
etcdstat/systemd.py
etcdstat/etcdparser/__init__.py
etcdstat/etcdparser/etcddoc.py
etcdstat/etcdparser/etcdparser.py
tw_etcdstat-0.1.1.post25.dist-info/LICENSE
tw_etcdstat-0.1.1.post25.dist-info/METADATA
tw_etcdstat-0.1.1.post25.dist-info/NOTICE
tw_etcdstat-0.1.1.post25.dist-info/WHEEL
tw_etcdstat-0.1.1.post25.dist-info/entry_points.txt
tw_etcdstat-0.1.1.post25.dist-info/top_level.txt
tw_etcdstat-0.1.1.post25.dist-info/RECORD
