Metadata-Version: 2.1
Name: tw-etcdstat
Version: 0.1.1.post25
Summary: Python system and service monitoring service
Home-page: https://github.com/thingswise/tw-etcdstat
Author: Alexander Lukichev
Author-email: alexander.lukichev@thingswise.com
License: Apache2
Platform: UNKNOWN
License-File: LICENSE
License-File: NOTICE
Requires-Dist: jinja2
Requires-Dist: psutil
Requires-Dist: cachetools (<4.0)
Requires-Dist: python-etcd
